kururu/__init__.py
kururu/nr.py
kururu/toolsdict.py
kururu/tool/__init__.py
kururu/tool/communication/__init__.py
kururu/tool/communication/lazycache.py
kururu/tool/communication/log.py
kururu/tool/communication/report.py
kururu/tool/dataflow/__init__.py
kururu/tool/dataflow/autoins.py
kururu/tool/dataflow/rank.py
kururu/tool/dataflow/sort.py
kururu/tool/enhancement/__init__.py
kururu/tool/enhancement/attribute/__init__.py
kururu/tool/enhancement/attribute/binarize.py
kururu/tool/enhancement/attribute/pca.py
kururu/tool/enhancement/attribute/abs/__init__.py
kururu/tool/enhancement/attribute/abs/transformer.py
kururu/tool/enhancement/instance/__init__.py
kururu/tool/enhancement/instance/sampling/__init__.py
kururu/tool/enhancement/instance/sampling/abs/__init__.py
kururu/tool/enhancement/instance/sampling/abs/sampler.py
kururu/tool/enhancement/instance/sampling/over/__init__.py
kururu/tool/enhancement/instance/sampling/over/rnd.py
kururu/tool/enhancement/instance/sampling/over/test_rnd.py
kururu/tool/enhancement/instance/sampling/under/__init__.py
kururu/tool/enhancement/instance/sampling/under/rnd.py
kururu/tool/enhancement/instance/sampling/under/sample.py
kururu/tool/enhancement/instance/sampling/under/test_rnd.py
kururu/tool/enhancement/instance/sampling/under/test_sample.py
kururu/tool/evaluation/__init__.py
kururu/tool/evaluation/metric.py
kururu/tool/evaluation/partition.py
kururu/tool/evaluation/split.py
kururu/tool/evaluation/summ.py
kururu/tool/evaluation/uncertainty.py
kururu/tool/evaluation/mixin/__init__.py
kururu/tool/evaluation/mixin/functioninspection.py
kururu/tool/evaluation/mixin/partitioning.py
kururu/tool/learning/__init__.py
kururu/tool/learning/supervised/__init__.py
kururu/tool/learning/supervised/abs/__init__.py
kururu/tool/learning/supervised/abs/predictor.py
kururu/tool/learning/supervised/classification/__init__.py
kururu/tool/learning/supervised/classification/svm.py
kururu/tool/manipulation/__init__.py
kururu/tool/manipulation/copy_.py
kururu-0.2102.23.dist-info/LICENSE
kururu-0.2102.23.dist-info/METADATA
kururu-0.2102.23.dist-info/WHEEL
kururu-0.2102.23.dist-info/top_level.txt
kururu-0.2102.23.dist-info/RECORD
