Metadata-Version: 2.1
Name: kururu
Version: 0.2102.23
Summary: Data Science
Home-page: https://github.com/davips/kururu
Author: Davi Pereira-Santos
Author-email: dpsabc@gmail.com
License: GPL3
Download-URL: https://github.com/davips/kururu/releases
Platform: UNKNOWN
Classifier: Intended Audience :: Science/Research
Classifier: License :: OSI Approved :: GNU General Public License v3 (GPLv3)
Classifier: Natural Language :: English
Classifier: Programming Language :: Python
Classifier: Topic :: Scientific/Engineering
Classifier: Programming Language :: Python :: 3.8
Requires-Dist: numpy
Requires-Dist: sklearn
Requires-Dist: liac-arff
Requires-Dist: imblearn
Requires-Dist: tatu
